gtirb_stack_stamp/__init__.py
gtirb_stack_stamp/__main__.py
gtirb_stack_stamp/stack_stamp.py
gtirb_stack_stamp-0.1.0.dist-info/DESCRIPTION.rst
gtirb_stack_stamp-0.1.0.dist-info/METADATA
gtirb_stack_stamp-0.1.0.dist-info/RECORD
gtirb_stack_stamp-0.1.0.dist-info/WHEEL
gtirb_stack_stamp-0.1.0.dist-info/entry_points.txt
gtirb_stack_stamp-0.1.0.dist-info/metadata.json
gtirb_stack_stamp-0.1.0.dist-info/top_level.txt
